PreKO/EDNAFULL
PreKO/InDel.py
PreKO/PreciseEdit.py
PreKO/__init__.py
PreKO/core.py
PreKO/params.py
PreKO/primeedit.py
PreKO/utils.py
preko-0.3.1.dist-info/METADATA
preko-0.3.1.dist-info/WHEEL
preko-0.3.1.dist-info/licenses/LICENSE
preko-0.3.1.dist-info/RECORD
