Metadata-Version: 2.4
Name: PreKO
Version: 0.3.1
Summary: PreKO: Precise KO system
Project-URL: Homepage, https://github.com/Goosang-Yu/PreKO
Project-URL: Repository, https://github.com/Goosang-Yu/PreKO
Project-URL: Source, https://github.com/Goosang-Yu/PreKO
Project-URL: Tracker, https://github.com/Goosang-Yu/PreKO/issues
Author-email: Goosang Yu <gsyu93@gmail.com>
License-File: LICENSE
Keywords: CRISPR,analysis,bioinformatics,gene,genetics,genome-editing,knockout,python
Classifier: Intended Audience :: Developers
Classifier: Intended Audience :: Science/Research
Classifier: Operating System :: MacOS :: MacOS X
Classifier: Operating System :: Microsoft :: Windows
Classifier: Operating System :: POSIX
Classifier: Operating System :: Unix
Classifier: Programming Language :: Python
Classifier: Programming Language :: Python :: 3 :: Only
Classifier: Programming Language :: Python :: 3.8
Classifier: Programming Language :: Python :: 3.9
Classifier: Programming Language :: Python :: 3.10
Classifier: Programming Language :: Python :: 3.11
Classifier: Topic :: Software Development
Classifier: Topic :: Software Development :: Libraries
Classifier: Topic :: Software Development :: Libraries :: Application Frameworks
Classifier: Topic :: Software Development :: Libraries :: Python Modules
Requires-Python: >=3.8
Requires-Dist: biopython
Requires-Dist: numpy
Requires-Dist: pandas
Requires-Dist: pydantic
Requires-Dist: tqdm
